{
  "project_info": {
    "project_number": "311761685163",
    "project_id": "core-venturo-66c92",
    "storage_bucket": "core-venturo-66c92.appspot.com"
  },
  "client": [
    {
      "client_info": {
        "mobilesdk_app_id": "1:311761685163:android:0803128f9768755e4d45ee",
        "android_client_info": {
          "package_name": "com.core.venturo"
        }
      },
      "oauth_client": [
        {
          "client_id": "311761685163-umenla20q7cju3i7schudautvvga4kd9.apps.googleusercontent.com",
          "client_type": 3
        }
      ],
      "api_key": [
        {
          "current_key": "AIzaSyAgbdGIWKiD8J-uslWsWzHI9qjtI7ngz7Q"
        }
      ],
      "services": {
        "appinvite_service": {
          "other_platform_oauth_client": [
            {
              "client_id": "311761685163-umenla20q7cju3i7schudautvvga4kd9.apps.googleusercontent.com",
              "client_type": 3
            }
          ]
        }
      }
    }
  ],
  "configuration_version": "1"
}